repvit/__init__.py
repvit-0.0.1.dev0.dist-info/METADATA
repvit-0.0.1.dev0.dist-info/WHEEL
repvit-0.0.1.dev0.dist-info/top_level.txt
repvit-0.0.1.dev0.dist-info/RECORD
